{
  "file": "HeistStorageLayout",
  "fields": [
    {
      "name": "Id",
      "type": "string",
      "unique": true
    },
    {
      "name": "Key0",
      "type": "u64"
    },
    {
      "name": "Flag0",
      "type": "bool"
    },
    {
      "name": "ButtonFile",
      "type": "string"
    },
    {
      "name": "Unknown3",
      "type": "i32"
    },
    {
      "name": "HeistJobsKey",
      "type": "longid",
      "ref": "HeistJobs"
    },
    {
      "name": "Unknown5",
      "type": "i32"
    },
    {
      "name": "Unknown6",
      "type": "i32"
    },
    {
      "name": "Unknown7",
      "type": "i32"
    },
    {
      "name": "Unknown8",
      "type": "i32"
    },
    {
      "name": "Unknown9",
      "type": "i32"
    },
    {
      "name": "Unknown10",
      "type": "i32"
    },
    {
      "name": "Key1",
      "type": "u64"
    }
  ]
}
